fluidattacks_zoho_sdk/__init__.py
fluidattacks_zoho_sdk/_decoders.py
fluidattacks_zoho_sdk/ids.py
fluidattacks_zoho_sdk/py.typed
fluidattacks_zoho_sdk/_http_client/__init__.py
fluidattacks_zoho_sdk/_http_client/_client.py
fluidattacks_zoho_sdk/_http_client/_core.py
fluidattacks_zoho_sdk/_http_client/paginate.py
fluidattacks_zoho_sdk/auth/__init__.py
fluidattacks_zoho_sdk/auth/_access.py
fluidattacks_zoho_sdk/auth/_core.py
fluidattacks_zoho_sdk/auth/_decode.py
fluidattacks_zoho_sdk/auth/_refresh.py
fluidattacks_zoho_sdk/auth/_revoke.py
fluidattacks_zoho_sdk/bulk_export/__init__.py
fluidattacks_zoho_sdk/bulk_export/_client.py
fluidattacks_zoho_sdk/bulk_export/_decode.py
fluidattacks_zoho_sdk/bulk_export/core.py
fluidattacks_zoho_sdk/bulk_export/utils.py
fluidattacks_zoho_sdk/zoho_desk/__init__.py
fluidattacks_zoho_sdk/zoho_desk/_client.py
fluidattacks_zoho_sdk/zoho_desk/_decode.py
fluidattacks_zoho_sdk/zoho_desk/core.py
fluidattacks_zoho_sdk/zoho_people/__init__.py
fluidattacks_zoho_sdk/zoho_people/_client.py
fluidattacks_zoho_sdk/zoho_people/_decode.py
fluidattacks_zoho_sdk/zoho_people/core.py
fluidattacks_zoho_sdk/zoho_people/decoders_ids.py
fluidattacks_zoho_sdk/zoho_people/ids.py
fluidattacks_zoho_sdk-3.0.0.dist-info/WHEEL
fluidattacks_zoho_sdk-3.0.0.dist-info/METADATA
fluidattacks_zoho_sdk-3.0.0.dist-info/RECORD
