Metadata-Version: 2.4
Name: fluidattacks_zoho_sdk
Version: 3.0.0
Summary: zoho SDK
Author-email: Product Team <development@fluidattacks.com>
Requires-Python: >=3.11
Requires-Dist: fa-purity >=2.5.0, <3.0.0
Requires-Dist: fluidattacks-etl-utils >=3.0.0, <4.0.0
Requires-Dist: pure-requests >=3.0.0, <4.0.0
